scsurv/__init__.py
scsurv/dataset.py
scsurv/exp.py
scsurv/modules.py
scsurv/utils.py
scsurv/workflow.py
scsurv/data/SKCM_checkpoint.pt
scsurv/data/SKCM_ref_5000genes.txt
scsurv/data/SKCM_umap_coordinates.csv
scsurv/data/tutolial_simulated_bulk.h5ad
scsurv/data/tutolial_simulated_sc_reference.h5ad
scsurv-0.2.1.dist-info/LICENSE
scsurv-0.2.1.dist-info/METADATA
scsurv-0.2.1.dist-info/WHEEL
scsurv-0.2.1.dist-info/top_level.txt
scsurv-0.2.1.dist-info/RECORD
