Metadata-Version: 2.1
Name: scsurv
Version: 0.2.1
Summary: a deep generative model for single-cell survival analysis
Author-email: Chikara Mizukoshi <mizucoscos@gmail.com>
License: MIT License
Project-URL: Homepage, https://github.com/3254c/scSurv
Project-URL: Issues, https://github.com/3254c/scSurv/issues
Keywords: bioinformatics,single-cell
Classifier: Programming Language :: Python :: 3
Classifier: License :: OSI Approved :: MIT License
Classifier: Operating System :: OS Independent
Requires-Python: >=3.8.16
License-File: LICENSE
Requires-Dist: torch>=1.13.1
Requires-Dist: lifelines>=0.27.8
Requires-Dist: scanpy>=1.9.5
Requires-Dist: pandas>=1.5.3
Requires-Dist: numpy>=1.23.5
Requires-Dist: matplotlib>=3.7.2
Requires-Dist: scipy>=1.10.1
